openhgnn/__init__.py
openhgnn/config.ini
openhgnn/config.py
openhgnn/experiment.py
openhgnn/auto/__init__.py
openhgnn/auto/hpo.py
openhgnn/auto/hpo_space.py
openhgnn/dataset/AbnormEventDetectionDataset.py
openhgnn/dataset/AdapropI_dataset.py
openhgnn/dataset/AdapropT_dataset.py
openhgnn/dataset/EdgeClassificationDataset.py
openhgnn/dataset/HGCLDataset.py
openhgnn/dataset/HypergraphDataset.py
openhgnn/dataset/Ingram_dataset.py
openhgnn/dataset/LTE_dataset.py
openhgnn/dataset/LinkPredictionDataset.py
openhgnn/dataset/NBF_dataset.py
openhgnn/dataset/NodeClassificationDataset.py
openhgnn/dataset/RecommendationDataset.py
openhgnn/dataset/SACN_dataset.py
openhgnn/dataset/__init__.py
openhgnn/dataset/academic_graph.py
openhgnn/dataset/adapter.py
openhgnn/dataset/alircd_dataset.py
openhgnn/dataset/base_dataset.py
openhgnn/dataset/gtn_dataset.py
openhgnn/dataset/hgb_dataset.py
openhgnn/dataset/knowledge_graph.py
openhgnn/dataset/mag_dataset.py
openhgnn/dataset/meirec_dataset.py
openhgnn/dataset/mg2vec_dataset.py
openhgnn/dataset/multigraph.py
openhgnn/dataset/oag_dataset.py
openhgnn/dataset/ohgb_dataset.py
openhgnn/dataset/utils.py
openhgnn/layers/AdapropI.py
openhgnn/layers/AdapropT.py
openhgnn/layers/EmbedLayer.py
openhgnn/layers/GeneralGNNLayer.py
openhgnn/layers/GeneralHGNNLayer.py
openhgnn/layers/HeteroGraphConv.py
openhgnn/layers/HeteroLinear.py
openhgnn/layers/MetapathConv.py
openhgnn/layers/SkipConnection.py
openhgnn/layers/__init__.py
openhgnn/layers/compgcn_layer.py
openhgnn/layers/rgcn_layer.py
openhgnn/layers/macro_layer/ATTConv.py
openhgnn/layers/macro_layer/SemanticConv.py
openhgnn/layers/macro_layer/__init__.py
openhgnn/layers/micro_layer/CompConv.py
openhgnn/layers/micro_layer/HGConv.py
openhgnn/layers/micro_layer/LSTM_conv.py
openhgnn/layers/micro_layer/__init__.py
openhgnn/models/AEHCL.py
openhgnn/models/ATT_HGCN.py
openhgnn/models/AdapropI.py
openhgnn/models/AdapropT.py
openhgnn/models/ComPILE.py
openhgnn-0.7.0.dist-info/METADATA
openhgnn-0.7.0.dist-info/RECORD
openhgnn-0.7.0.dist-info/WHEEL
openhgnn-0.7.0.dist-info/top_level.txt
